Workbook

Sheet Tổng quan HSK 1-6
A1: THƯ VIỆN HSK 2.0 (6 CẤP ĐỘ: HSK 1 – HSK 6) | XIEHANZI.COM
A2: Bảng tổng hợp 6 cấp độ, 146 bài học (Giáo trình Chuẩn HSK), 184 chủ đề và hệ thống từ vựng phân chia chi tiết theo bài học
A4: Cấp độ HSK | B4: Phân cấp trình độ | C4: Số bài học | D4: Số chủ đề | E4: Từ vựng chuẩn (Theo cấp) | F4: Tổng lượt từ trong bài học | G4: Số từ trích xuất chi tiết | H4: Số điểm ngữ pháp | I4: Thời lượng ước tính (Giờ) | J4: Link trang cấp độ XieHanzi
A5: HSK 1 | B5: Sơ cấp (初级) | C5: 15 | D5: 13 | E5: 93 | F5: 164 | G5: =COUNTA('HSK 1'!H5:H169) | H5: 46 | I5: 16 | J5: https://xiehanzi.com/thu-vien-hsk/hsk-1/
A6: HSK 2 | B6: Sơ cấp (初级) | C6: 15 | D6: 12 | E6: 107 | F6: 172 | G6: =COUNTA('HSK 2'!H5:H176) | H6: 44 | I6: 18 | J6: https://xiehanzi.com/thu-vien-hsk/hsk-2/
A7: HSK 3 | B7: Trung cấp (中级) | C7: 20 | D7: 16 | E7: 273 | F7: 311 | G7: =COUNTA('HSK 3'!H5:H317) | H7: 47 | I7: 46 | J7: https://xiehanzi.com/thu-vien-hsk/hsk-3/
A8: HSK 4 | B8: Trung cấp (中级) | C8: 20 | D8: 26 | E8: 599 | F8: 619 | G8: =COUNTA('HSK 4'!H5:H626) | H8: 40 | I8: 100 | J8: https://xiehanzi.com/thu-vien-hsk/hsk-4/
A9: HSK 5 | B9: Cao cấp (高级) | C9: 36 | D9: 43 | E9: 1282 | F9: 1601 | G9: =COUNTA('HSK 5'!H5:H1252) | H9: 101 | I9: 214 | J9: https://xiehanzi.com/thu-vien-hsk/hsk-5/
A10: HSK 6 | B10: Cao cấp (高级) | C10: 40 | D10: 74 | E10: 2593 | F10: 2516 | G10: =COUNTA('HSK 6'!H5:H1577) | H10: 63 | I10: 432 | J10: https://xiehanzi.com/thu-vien-hsk/hsk-6/
A11: Tổng cộng | B11: 6 cấp độ (HSK 1 – 6) | C11: =SUM(C5:C10) | D11: =SUM(D5:D10) | E11: =SUM(E5:E10) | F11: =SUM(F5:F10) | G11: =SUM(G5:G10) | H11: =SUM(H5:H10) | I11: =SUM(I5:I10) | J11: https://xiehanzi.com/thu-vien-hsk/

Sheet Mục lục 146 Bài học
A1: MỤC LỤC CHI TIẾT TOÀN BỘ 146 BÀI HỌC TỪ HSK 1 ĐẾN HSK 6 | XIEHANZI.COM
A2: Danh sách đầy đủ 146 bài học theo Giáo trình Chuẩn HSK (HSK Standard Course), kèm chủ đề, số lượng từ vựng và đường dẫn trực tiếp
A4: STT | B4: Cấp HSK | C4: Mã bài | D4: Tên bài học (Tiếng Việt) | E4: Tên bài học (Tiếng Trung) | F4: Phiên âm Pinyin | G4: Chủ đề / Đơn nguyên (Unit) | H4: Số từ trích xuất | I4: Số từ trên XieHanzi | J4: Link bài học trên XieHanzi
A5: 1 | B5: HSK 1 | C5: Bài 01 | D5: Xin chào | E5: 你好 | F5: Nǐ hǎo | G5: Chào hỏi & Giao tiếp cơ bản | H5: 6 | I5: 6 | J5: https://xiehanzi.com/thu-vien-hsk/hsk-1/bai-hoc/bai-1-xin-chao/
A6: 2 | B6: HSK 1 | C6: Bài 02 | D6: Cảm ơn bạn | E6: 谢谢你 | F6: Xièxie nǐ | G6: Lịch sự & Cảm ơn | H6: 4 | I6: 4 | J6: https://xiehanzi.com/thu-vien-hsk/hsk-1/bai-hoc/bai-2-cam-on-ban/
A7: 3 | B7: HSK 1 | C7: Bài 03 | D7: Bạn tên là gì? | E7: 你叫什么名字 | F7: Nǐ jiào shénme míngzi | G7: Giới thiệu bản thân & Quốc tịch | H7: 9 | I7: 9 | J7: https://xiehanzi.com/thu-vien-hsk/hsk-1/bai-hoc/bai-3-ban-ten-la-gi/
A8: 4 | B8: HSK 1 | C8: Bài 04 | D8: Cô ấy là giáo viên tiếng Hán của tôi | E8: 她是我的汉语老师 | F8: Tā shì wǒ de Hànyǔ lǎoshī | G8: Trường học & Bạn bè | H8: 10 | I8: 9 | J8: https://xiehanzi.com/thu-vien-hsk/hsk-1/bai-hoc/bai-4-co-ay-la-giao-vien-tieng-han-cua-toi/
A9: 5 | B9: HSK 1 | C9: Bài 05 | D9: Con gái cô ấy năm nay 20 tuổi | E9: 她女儿今年二十岁 | F9: Tā nǚ'ér jīnnián èrshí suì | G9: Gia đình & Tuổi tác | H9: 10 | I9: 10 | J9: https://xiehanzi.com/thu-vien-hsk/hsk-1/bai-hoc/bai-5-con-gai-co-ay-nam-nay-20-tuoi/
A10: 6 | B10: HSK 1 | C10: Bài 06 | D10: Tôi biết nói tiếng Hán | E10: 我会说汉语 | F10: Wǒ huì shuō Hànyǔ | G10: Kỹ năng & Ngôn ngữ | H10: 12 | I10: 12 | J10: https://xiehanzi.com/thu-vien-hsk/hsk-1/bai-hoc/bai-6-toi-biet-noi-tieng-han/
A11: 7 | B11: HSK 1 | C11: Bài 07 | D11: Hôm nay là ngày mấy? | E11: 今天几号 | F11: Jīntiān jǐ hào | G11: Thời gian & Ngày tháng | H11: 12 | I11: 12 | J11: https://xiehanzi.com/thu-vien-hsk/hsk-1/bai-hoc/bai-7-hom-nay-la-ngay-may/
A12: 8 | B12: HSK 1 | C12: Bài 08 | D12: Tôi muốn uống trà | E12: 我想喝茶 | F12: Wǒ xiǎng hē chá | G12: Thức ăn, Đồ uống & Mua sắm | H12: 15 | I12: 15 | J12: https://xiehanzi.com/thu-vien-hsk/hsk-1/bai-hoc/bai-8-toi-muon-uong-tra/
A13: 9 | B13: HSK 1 | C13: Bài 09 | D13: Con trai bạn làm việc ở đâu? | E13: 你儿子在哪儿工作 | F13: Nǐ érzi zài nǎr gōngzuò | G13: Nơi chốn & Nghề nghiệp | H13: 13 | I13: 13 | J13: https://xiehanzi.com/thu-vien-hsk/hsk-1/bai-hoc/bai-9-con-trai-ban-lam-viec-o-dau/
A14: 10 | B14: HSK 1 | C14: Bài 10 | D14: Tôi có thể ngồi đây không? | E14: 我能坐这儿吗 | F14: Wǒ néng zuò zhèr ma | G14: Vị trí & Đồ vật | H14: 12 | I14: 12 | J14: https://xiehanzi.com/thu-vien-hsk/hsk-1/bai-hoc/bai-10-toi-co-the-ngoi-day-khong/
A15: 11 | B15: HSK 1 | C15: Bài 11 | D15: Bây giờ mấy giờ rồi? | E15: 现在几点 | F15: Xiànzài jǐ diǎn | G15: Thời gian & Sinh hoạt | H15: 11 | I15: 11 | J15: https://xiehanzi.com/thu-vien-hsk/hsk-1/bai-hoc/bai-11-bay-gio-may-gio-roi/
A16: 12 | B16: HSK 1 | C16: Bài 12 | D16: Ngày mai thời tiết thế nào? | E16: 明天天气怎么样 | F16: Míngtiān tiānqì zěnmeyàng | G16: Thời tiết & Sức khỏe | H16: 15 | I16: 15 | J16: https://xiehanzi.com/thu-vien-hsk/hsk-1/bai-hoc/bai-12-ngay-mai-thoi-tiet-the-nao/
... A150: 146 | B150: HSK 6 | C150: Bài 40 | D150: Siêu năng lực của con người có làm thay đổi kỷ lục thế giới không? | E150: 人类超能力会改变世界纪录吗 | F150: Rénlèi chāonénglì huì gǎibiàn shìjiè jìlù ma | G150: Xã hội và thời đại (社会与时代) | H150: 29 | I150: 59 | J150: https://xiehanzi.com/thu-vien-hsk/hsk-6/bai-hoc/bai-40-sieu-nang-luc-cua-con-nguoi-co-lam-thay-doi-ky-luc-the-gioi-khong/
B151: Tổng cộng | C151: 146 bài | D151: Toàn bộ 146 bài học Giáo trình Chuẩn HSK 1–6 | H151: =SUM(H5:H150) | I151: =SUM(I5:I150)

Sheet HSK 1
A1: DANH SÁCH BÀI HỌC & TỪ VỰNG HSK 1 (SƠ CẤP) — THƯ VIỆN XIEHANZI
A2: Trình độ: Sơ cấp | Số bài học: 15 bài | Số chủ đề: 13 chủ đề | Từ chuẩn cấp HSK 1: 93 từ | Tổng lượt từ trong bài: 164 từ | Ngữ pháp: 46 điểm | Thời lượng: ~16 giờ | Nguồn: https://xiehanzi.com/thu-vien-hsk/hsk-1/
A4: STT | B4: Cấp HSK | C4: Bài số | D4: Tên bài học (Tiếng Việt) | E4: Tên bài học (Tiếng Trung) | F4: Chủ đề / Đơn nguyên | G4: STT trong bài | H4: Từ vựng (Chữ Hán) | I4: Phiên âm (Pinyin) | J4: Từ loại | K4: Nghĩa tiếng Việt | L4: Link bài học XieHanzi
A5: 1 | B5: HSK 1 | C5: Bài 01 | D5: Xin chào | E5: 你好 | F5: Chào hỏi & Giao tiếp cơ bản | G5: 1 | H5: 你 | I5: nǐ | J5: Đại từ | K5: bạn, anh, chị (ngôi thứ 2 số ít) | L5: https://xiehanzi.com/thu-vien-hsk/hsk-1/bai-hoc/bai-1-xin-chao/
A6: 2 | B6: HSK 1 | C6: Bài 01 | D6: Xin chào | E6: 你好 | F6: Chào hỏi & Giao tiếp cơ bản | G6: 2 | H6: 好 | I6: hǎo | J6: Tính từ | K6: tốt, khỏe, hay | L6: https://xiehanzi.com/thu-vien-hsk/hsk-1/bai-hoc/bai-1-xin-chao/
A7: 3 | B7: HSK 1 | C7: Bài 01 | D7: Xin chào | E7: 你好 | F7: Chào hỏi & Giao tiếp cơ bản | G7: 3 | H7: 您 | I7: nín | J7: Đại từ | K7: ông, bà, ngài (ngôi thứ 2 kính trọng) | L7: https://xiehanzi.com/thu-vien-hsk/hsk-1/bai-hoc/bai-1-xin-chao/
A8: 4 | B8: HSK 1 | C8: Bài 01 | D8: Xin chào | E8: 你好 | F8: Chào hỏi & Giao tiếp cơ bản | G8: 4 | H8: 你们 | I8: nǐ men | J8: Đại từ | K8: các bạn, các anh, các chị | L8: https://xiehanzi.com/thu-vien-hsk/hsk-1/bai-hoc/bai-1-xin-chao/
A9: 5 | B9: HSK 1 | C9: Bài 01 | D9: Xin chào | E9: 你好 | F9: Chào hỏi & Giao tiếp cơ bản | G9: 5 | H9: 对不起 | I9: duì bu qǐ | J9: Động từ | K9: xin lỗi | L9: https://xiehanzi.com/thu-vien-hsk/hsk-1/bai-hoc/bai-1-xin-chao/
A10: 6 | B10: HSK 1 | C10: Bài 01 | D10: Xin chào | E10: 你好 | F10: Chào hỏi & Giao tiếp cơ bản | G10: 6 | H10: 没关系 | I10: méi guān xi | J10: Động từ | K10: không sao, không có gì | L10: https://xiehanzi.com/thu-vien-hsk/hsk-1/bai-hoc/bai-1-xin-chao/
A11: 7 | B11: HSK 1 | C11: Bài 02 | D11: Cảm ơn bạn | E11: 谢谢你 | F11: Lịch sự & Cảm ơn | G11: 1 | H11: 谢谢 | I11: xiè xie | J11: Động từ | K11: cảm ơn | L11: https://xiehanzi.com/thu-vien-hsk/hsk-1/bai-hoc/bai-2-cam-on-ban/
A12: 8 | B12: HSK 1 | C12: Bài 02 | D12: Cảm ơn bạn | E12: 谢谢你 | F12: Lịch sự & Cảm ơn | G12: 2 | H12: 不 | I12: bù | J12: Phó từ | K12: không | L12: https://xiehanzi.com/thu-vien-hsk/hsk-1/bai-hoc/bai-2-cam-on-ban/
A13: 9 | B13: HSK 1 | C13: Bài 02 | D13: Cảm ơn bạn | E13: 谢谢你 | F13: Lịch sự & Cảm ơn | G13: 3 | H13: 不客气 | I13: bù kè qi | J13: Động từ | K13: đừng khách sáo, không có chi | L13: https://xiehanzi.com/thu-vien-hsk/hsk-1/bai-hoc/bai-2-cam-on-ban/
A14: 10 | B14: HSK 1 | C14: Bài 02 | D14: Cảm ơn bạn | E14: 谢谢你 | F14: Lịch sự & Cảm ơn | G14: 4 | H14: 再见 | I14: zài jiàn | J14: Động từ | K14: tạm biệt, hẹn gặp lại | L14: https://xiehanzi.com/thu-vien-hsk/hsk-1/bai-hoc/bai-2-cam-on-ban/
A15: 11 | B15: HSK 1 | C15: Bài 03 | D15: Bạn tên là gì? | E15: 你叫什么名字 | F15: Giới thiệu bản thân & Quốc tịch | G15: 1 | H15: 叫 | I15: jiào | J15: Động từ | K15: gọi, tên là | L15: https://xiehanzi.com/thu-vien-hsk/hsk-1/bai-hoc/bai-3-ban-ten-la-gi/
A16: 12 | B16: HSK 1 | C16: Bài 03 | D16: Bạn tên là gì? | E16: 你叫什么名字 | F16: Giới thiệu bản thân & Quốc tịch | G16: 2 | H16: 什么 | I16: shén me | J16: Đại từ | K16: cái gì, gì | L16: https://xiehanzi.com/thu-vien-hsk/hsk-1/bai-hoc/bai-3-ban-ten-la-gi/
... A169: 165 | B169: HSK 1 | C169: Bài 15 | D169: Tôi đến bằng máy bay | E169: 我是坐飞机来的 | F169: Giao thông & Đi lại | G169: 9 | H169: 飞机 | I169: fēi jī | J169: Danh từ | K169: máy bay | L169: https://xiehanzi.com/thu-vien-hsk/hsk-1/bai-hoc/bai-15-toi-den-bang-may-bay/
B170: Tổng cộng | C170: 15 bài học | D170: Toàn bộ từ vựng HSK 1 (15 bài) | F170: 13 chủ đề | G170: =COUNTA(H5:H169) | K170: Tổng số mục từ vựng trong 15 bài học HSK 1: 165 từ

Sheet HSK 2
A1: DANH SÁCH BÀI HỌC & TỪ VỰNG HSK 2 (SƠ CẤP) — THƯ VIỆN XIEHANZI
A2: Trình độ: Sơ cấp | Số bài học: 15 bài | Số chủ đề: 12 chủ đề | Từ chuẩn cấp HSK 2: 107 từ | Tổng lượt từ trong bài: 172 từ | Ngữ pháp: 44 điểm | Thời lượng: ~18 giờ | Nguồn: https://xiehanzi.com/thu-vien-hsk/hsk-2/
A4: STT | B4: Cấp HSK | C4: Bài số | D4: Tên bài học (Tiếng Việt) | E4: Tên bài học (Tiếng Trung) | F4: Chủ đề / Đơn nguyên | G4: STT trong bài | H4: Từ vựng (Chữ Hán) | I4: Phiên âm (Pinyin) | J4: Từ loại | K4: Nghĩa tiếng Việt | L4: Link bài học XieHanzi
A5: 1 | B5: HSK 2 | C5: Bài 01 | D5: Tháng 9 đi Bắc Kinh du lịch là tốt nhất | E5: 九月去北京旅游最好 | F5: Du lịch & Thể thao | G5: 1 | H5: 旅游 | I5: lǚ yóu | J5: Động từ | K5: du lịch | L5: https://xiehanzi.com/thu-vien-hsk/hsk-2/bai-hoc/bai-1-thang-9-di-bac-kinh-du-lich-la-tot-nhat/
A6: 2 | B6: HSK 2 | C6: Bài 01 | D6: Tháng 9 đi Bắc Kinh du lịch là tốt nhất | E6: 九月去北京旅游最好 | F6: Du lịch & Thể thao | G6: 2 | H6: 觉得 | I6: jué de | J6: Động từ | K6: cảm thấy, cho rằng | L6: https://xiehanzi.com/thu-vien-hsk/hsk-2/bai-hoc/bai-1-thang-9-di-bac-kinh-du-lich-la-tot-nhat/
A7: 3 | B7: HSK 2 | C7: Bài 01 | D7: Tháng 9 đi Bắc Kinh du lịch là tốt nhất | E7: 九月去北京旅游最好 | F7: Du lịch & Thể thao | G7: 3 | H7: 最 | I7: zuì | J7: Phó từ | K7: nhất (so sánh bậc nhất) | L7: https://xiehanzi.com/thu-vien-hsk/hsk-2/bai-hoc/bai-1-thang-9-di-bac-kinh-du-lich-la-tot-nhat/
A8: 4 | B8: HSK 2 | C8: Bài 01 | D8: Tháng 9 đi Bắc Kinh du lịch là tốt nhất | E8: 九月去北京旅游最好 | F8: Du lịch & Thể thao | G8: 4 | H8: 为什么 | I8: wèi shén me | J8: Đại từ | K8: tại sao, vì sao | L8: https://xiehanzi.com/thu-vien-hsk/hsk-2/bai-hoc/bai-1-thang-9-di-bac-kinh-du-lich-la-tot-nhat/
A9: 5 | B9: HSK 2 | C9: Bài 01 | D9: Tháng 9 đi Bắc Kinh du lịch là tốt nhất | E9: 九月去北京旅游最好 | F9: Du lịch & Thể thao | G9: 5 | H9: 也 | I9: yě | J9: Phó từ | K9: cũng | L9: https://xiehanzi.com/thu-vien-hsk/hsk-2/bai-hoc/bai-1-thang-9-di-bac-kinh-du-lich-la-tot-nhat/
A10: 6 | B10: HSK 2 | C10: Bài 01 | D10: Tháng 9 đi Bắc Kinh du lịch là tốt nhất | E10: 九月去北京旅游最好 | F10: Du lịch & Thể thao | G10: 6 | H10: 运动 | I10: yùn dòng | J10: Động từ / Danh từ | K10: vận động; thể thao | L10: https://xiehanzi.com/thu-vien-hsk/hsk-2/bai-hoc/bai-1-thang-9-di-bac-kinh-du-lich-la-tot-nhat/
A11: 7 | B11: HSK 2 | C11: Bài 01 | D11: Tháng 9 đi Bắc Kinh du lịch là tốt nhất | E11: 九月去北京旅游最好 | F11: Du lịch & Thể thao | G11: 7 | H11: 踢足球 | I11: tī zú qiú | J11: Động từ | K11: đá bóng | L11: https://xiehanzi.com/thu-vien-hsk/hsk-2/bai-hoc/bai-1-thang-9-di-bac-kinh-du-lich-la-tot-nhat/
A12: 8 | B12: HSK 2 | C12: Bài 01 | D12: Tháng 9 đi Bắc Kinh du lịch là tốt nhất | E12: 九月去北京旅游最好 | F12: Du lịch & Thể thao | G12: 8 | H12: 一起 | I12: yī qǐ | J12: Phó từ | K12: cùng nhau | L12: https://xiehanzi.com/thu-vien-hsk/hsk-2/bai-hoc/bai-1-thang-9-di-bac-kinh-du-lich-la-tot-nhat/
A13: 9 | B13: HSK 2 | C13: Bài 01 | D13: Tháng 9 đi Bắc Kinh du lịch là tốt nhất | E13: 九月去北京旅游最好 | F13: Du lịch & Thể thao | G13: 9 | H13: 要 | I13: yào | J13: Động từ năng nguyện | K13: muốn, cần, phải, sắp | L13: https://xiehanzi.com/thu-vien-hsk/hsk-2/bai-hoc/bai-1-thang-9-di-bac-kinh-du-lich-la-tot-nhat/
A14: 10 | B14: HSK 2 | C14: Bài 01 | D14: Tháng 9 đi Bắc Kinh du lịch là tốt nhất | E14: 九月去北京旅游最好 | F14: Du lịch & Thể thao | G14: 10 | H14: 新 | I14: xīn | J14: Tính từ | K14: mới | L14: https://xiehanzi.com/thu-vien-hsk/hsk-2/bai-hoc/bai-1-thang-9-di-bac-kinh-du-lich-la-tot-nhat/
A15: 11 | B15: HSK 2 | C15: Bài 01 | D15: Tháng 9 đi Bắc Kinh du lịch là tốt nhất | E15: 九月去北京旅游最好 | F15: Du lịch & Thể thao | G15: 11 | H15: 它 | I15: tā | J15: Đại từ | K15: nó (chỉ vật, con vật) | L15: https://xiehanzi.com/thu-vien-hsk/hsk-2/bai-hoc/bai-1-thang-9-di-bac-kinh-du-lich-la-tot-nhat/
A16: 12 | B16: HSK 2 | C16: Bài 01 | D16: Tháng 9 đi Bắc Kinh du lịch là tốt nhất | E16: 九月去北京旅游最好 | F16: Du lịch & Thể thao | G16: 12 | H16: 眼睛 | I16: yǎn jing | J16: Danh từ | K16: đôi mắt, mắt | L16: https://xiehanzi.com/thu-vien-hsk/hsk-2/bai-hoc/bai-1-thang-9-di-bac-kinh-du-lich-la-tot-nhat/
... A176: 172 | B176: HSK 2 | C176: Bài 15 | D176: Năm mới sắp đến rồi | E176: 新年就要到了 | F176: Lễ tết & Sự kiện | G176: 8 | H176: 阴 | I176: yīn | J176: Tính từ | K176: âm u, nhiều mây | L176: https://xiehanzi.com/thu-vien-hsk/hsk-2/bai-hoc/bai-15-nam-moi-sap-den-roi/
B177: Tổng cộng | C177: 15 bài học | D177: Toàn bộ từ vựng HSK 2 (15 bài) | F177: 12 chủ đề | G177: =COUNTA(H5:H176) | K177: Tổng số mục từ vựng trong 15 bài học HSK 2: 172 từ

Sheet HSK 3
A1: DANH SÁCH BÀI HỌC & TỪ VỰNG HSK 3 (TRUNG CẤP) — THƯ VIỆN XIEHANZI
A2: Trình độ: Trung cấp | Số bài học: 20 bài | Số chủ đề: 16 chủ đề | Từ chuẩn cấp HSK 3: 273 từ | Tổng lượt từ trong bài: 311 từ | Ngữ pháp: 47 điểm | Thời lượng: ~46 giờ | Nguồn: https://xiehanzi.com/thu-vien-hsk/hsk-3/
A4: STT | B4: Cấp HSK | C4: Bài số | D4: Tên bài học (Tiếng Việt) | E4: Tên bài học (Tiếng Trung) | F4: Chủ đề / Đơn nguyên | G4: STT trong bài | H4: Từ vựng (Chữ Hán) | I4: Phiên âm (Pinyin) | J4: Từ loại | K4: Nghĩa tiếng Việt | L4: Link bài học XieHanzi
A5: 1 | B5: HSK 3 | C5: Bài 01 | D5: Cuối tuần bạn có dự định gì? | E5: 周末你有什么打算 | F5: Kế hoạch & Giải trí | G5: 1 | H5: 周末 | I5: zhōu mò | J5: Danh từ | K5: cuối tuần | L5: https://xiehanzi.com/thu-vien-hsk/hsk-3/bai-hoc/bai-1-cuoi-tuan-ban-co-du-dinh-gi/
A6: 2 | B6: HSK 3 | C6: Bài 01 | D6: Cuối tuần bạn có dự định gì? | E6: 周末你有什么打算 | F6: Kế hoạch & Giải trí | G6: 2 | H6: 打算 | I6: dǎ suàn | J6: Động từ / Danh từ | K6: dự định, tính toán; kế hoạch | L6: https://xiehanzi.com/thu-vien-hsk/hsk-3/bai-hoc/bai-1-cuoi-tuan-ban-co-du-dinh-gi/
A7: 3 | B7: HSK 3 | C7: Bài 01 | D7: Cuối tuần bạn có dự định gì? | E7: 周末你有什么打算 | F7: Kế hoạch & Giải trí | G7: 3 | H7: 啊 | I7: a | J7: Trợ từ | K7: à, ừ, nhỉ (trợ từ ngữ khí) | L7: https://xiehanzi.com/thu-vien-hsk/hsk-3/bai-hoc/bai-1-cuoi-tuan-ban-co-du-dinh-gi/
A8: 4 | B8: HSK 3 | C8: Bài 01 | D8: Cuối tuần bạn có dự định gì? | E8: 周末你有什么打算 | F8: Kế hoạch & Giải trí | G8: 4 | H8: 跟 | I8: gēn | J8: Giới từ / Liên từ | K8: cùng, với; theo | L8: https://xiehanzi.com/thu-vien-hsk/hsk-3/bai-hoc/bai-1-cuoi-tuan-ban-co-du-dinh-gi/
A9: 5 | B9: HSK 3 | C9: Bài 01 | D9: Cuối tuần bạn có dự định gì? | E9: 周末你有什么打算 | F9: Kế hoạch & Giải trí | G9: 5 | H9: 一直 | I9: yī zhí | J9: Phó từ | K9: luôn, suốt, thẳng | L9: https://xiehanzi.com/thu-vien-hsk/hsk-3/bai-hoc/bai-1-cuoi-tuan-ban-co-du-dinh-gi/
A10: 6 | B10: HSK 3 | C10: Bài 01 | D10: Cuối tuần bạn có dự định gì? | E10: 周末你有什么打算 | F10: Kế hoạch & Giải trí | G10: 6 | H10: 游戏 | I10: yóu xì | J10: Danh từ | K10: trò chơi, game | L10: https://xiehanzi.com/thu-vien-hsk/hsk-3/bai-hoc/bai-1-cuoi-tuan-ban-co-du-dinh-gi/
A11: 7 | B11: HSK 3 | C11: Bài 01 | D11: Cuối tuần bạn có dự định gì? | E11: 周末你有什么打算 | F11: Kế hoạch & Giải trí | G11: 7 | H11: 作业 | I11: zuò yè | J11: Danh từ | K11: bài tập về nhà | L11: https://xiehanzi.com/thu-vien-hsk/hsk-3/bai-hoc/bai-1-cuoi-tuan-ban-co-du-dinh-gi/
A12: 8 | B12: HSK 3 | C12: Bài 01 | D12: Cuối tuần bạn có dự định gì? | E12: 周末你有什么打算 | F12: Kế hoạch & Giải trí | G12: 8 | H12: 着急 | I12: zháo jí | J12: Tính từ | K12: lo lắng, sốt ruột, vội vàng | L12: https://xiehanzi.com/thu-vien-hsk/hsk-3/bai-hoc/bai-1-cuoi-tuan-ban-co-du-dinh-gi/
A13: 9 | B13: HSK 3 | C13: Bài 01 | D13: Cuối tuần bạn có dự định gì? | E13: 周末你有什么打算 | F13: Kế hoạch & Giải trí | G13: 9 | H13: 复习 | I13: fù xí | J13: Động từ | K13: ôn tập | L13: https://xiehanzi.com/thu-vien-hsk/hsk-3/bai-hoc/bai-1-cuoi-tuan-ban-co-du-dinh-gi/
A14: 10 | B14: HSK 3 | C14: Bài 01 | D14: Cuối tuần bạn có dự định gì? | E14: 周末你有什么打算 | F14: Kế hoạch & Giải trí | G14: 10 | H14: 南方 | I14: nán fāng | J14: Danh từ | K14: miền Nam, phương Nam | L14: https://xiehanzi.com/thu-vien-hsk/hsk-3/bai-hoc/bai-1-cuoi-tuan-ban-co-du-dinh-gi/
A15: 11 | B15: HSK 3 | C15: Bài 01 | D15: Cuối tuần bạn có dự định gì? | E15: 周末你有什么打算 | F15: Kế hoạch & Giải trí | G15: 11 | H15: 北方 | I15: běi fāng | J15: Danh từ | K15: miền Bắc, phương Bắc | L15: https://xiehanzi.com/thu-vien-hsk/hsk-3/bai-hoc/bai-1-cuoi-tuan-ban-co-du-dinh-gi/
A16: 12 | B16: HSK 3 | C16: Bài 01 | D16: Cuối tuần bạn có dự định gì? | E16: 周末你有什么打算 | F16: Kế hoạch & Giải trí | G16: 12 | H16: 面包 | I16: miàn bāo | J16: Danh từ | K16: bánh mì | L16: https://xiehanzi.com/thu-vien-hsk/hsk-3/bai-hoc/bai-1-cuoi-tuan-ban-co-du-dinh-gi/
... A317: 313 | B317: HSK 3 | C317: Bài 20 | D317: Tôi bị anh ấy ảnh hưởng. | E317: 我被他影响了 | F317: Giải quyết vấn đề & Cảm xúc | G317: 13 | H317: 多么 | I317: duō me | J317: Phó từ | K317: bao nhiêu, biết bao (cảm thán) | L317: https://xiehanzi.com/thu-vien-hsk/hsk-3/bai-hoc/bai-20-toi-bi-anh-ay-anh-huong/
B318: Tổng cộng | C318: 20 bài học | D318: Toàn bộ từ vựng HSK 3 (20 bài) | F318: 16 chủ đề | G318: =COUNTA(H5:H317) | K318: Tổng số mục từ vựng trong 20 bài học HSK 3: 313 từ

Sheet HSK 4
A1: DANH SÁCH BÀI HỌC & TỪ VỰNG HSK 4 (TRUNG CẤP) — THƯ VIỆN XIEHANZI
A2: Trình độ: Trung cấp | Số bài học: 20 bài | Số chủ đề: 26 chủ đề | Từ chuẩn cấp HSK 4: 599 từ | Tổng lượt từ trong bài: 619 từ | Ngữ pháp: 40 điểm | Thời lượng: ~100 giờ | Nguồn: https://xiehanzi.com/thu-vien-hsk/hsk-4/
A4: STT | B4: Cấp HSK | C4: Bài số | D4: Tên bài học (Tiếng Việt) | E4: Tên bài học (Tiếng Trung) | F4: Chủ đề / Đơn nguyên | G4: STT trong bài | H4: Từ vựng (Chữ Hán) | I4: Phiên âm (Pinyin) | J4: Từ loại | K4: Nghĩa tiếng Việt | L4: Link bài học XieHanzi
A5: 1 | B5: HSK 4 | C5: Bài 01 | D5: Tình yêu đơn giản | E5: 简单的爱情 | F5: Tình yêu & Hôn nhân | G5: 1 | H5: 法律 | I5: fǎ lǜ | J5: Danh từ | K5: pháp luật | L5: https://xiehanzi.com/thu-vien-hsk/hsk-4/bai-hoc/bai-1-tinh-yeu-don-gian/
A6: 2 | B6: HSK 4 | C6: Bài 01 | D6: Tình yêu đơn giản | E6: 简单的爱情 | F6: Tình yêu & Hôn nhân | G6: 2 | H6: 俩 | I6: liǎ | J6: Số lượng từ | K6: hai (người) | L6: https://xiehanzi.com/thu-vien-hsk/hsk-4/bai-hoc/bai-1-tinh-yeu-don-gian/
A7: 3 | B7: HSK 4 | C7: Bài 01 | D7: Tình yêu đơn giản | E7: 简单的爱情 | F7: Tình yêu & Hôn nhân | G7: 3 | H7: 印象 | I7: yìn xiàng | J7: Danh từ | K7: ấn tượng | L7: https://xiehanzi.com/thu-vien-hsk/hsk-4/bai-hoc/bai-1-tinh-yeu-don-gian/
A8: 4 | B8: HSK 4 | C8: Bài 01 | D8: Tình yêu đơn giản | E8: 简单的爱情 | F8: Tình yêu & Hôn nhân | G8: 4 | H8: 深 | I8: shēn | J8: Tính từ | K8: sâu, sâu sắc, đậm | L8: https://xiehanzi.com/thu-vien-hsk/hsk-4/bai-hoc/bai-1-tinh-yeu-don-gian/
A9: 5 | B9: HSK 4 | C9: Bài 01 | D9: Tình yêu đơn giản | E9: 简单的爱情 | F9: Tình yêu & Hôn nhân | G9: 5 | H9: 熟悉 | I9: shú xī | J9: Động từ / Tính từ | K9: quen thuộc, nắm rõ | L9: https://xiehanzi.com/thu-vien-hsk/hsk-4/bai-hoc/bai-1-tinh-yeu-don-gian/
A10: 6 | B10: HSK 4 | C10: Bài 01 | D10: Tình yêu đơn giản | E10: 简单的爱情 | F10: Tình yêu & Hôn nhân | G10: 6 | H10: 不仅 | I10: bù jǐn | J10: Liên từ | K10: không những | L10: https://xiehanzi.com/thu-vien-hsk/hsk-4/bai-hoc/bai-1-tinh-yeu-don-gian/
A11: 7 | B11: HSK 4 | C11: Bài 01 | D11: Tình yêu đơn giản | E11: 简单的爱情 | F11: Tình yêu & Hôn nhân | G11: 7 | H11: 性格 | I11: xìng gé | J11: Danh từ | K11: tính cách | L11: https://xiehanzi.com/thu-vien-hsk/hsk-4/bai-hoc/bai-1-tinh-yeu-don-gian/
A12: 8 | B12: HSK 4 | C12: Bài 01 | D12: Tình yêu đơn giản | E12: 简单的爱情 | F12: Tình yêu & Hôn nhân | G12: 8 | H12: 开玩笑 | I12: kāi wán xiào | J12: Động từ | K12: nói đùa, trêu đùa | L12: https://xiehanzi.com/thu-vien-hsk/hsk-4/bai-hoc/bai-1-tinh-yeu-don-gian/
A13: 9 | B13: HSK 4 | C13: Bài 01 | D13: Tình yêu đơn giản | E13: 简单的爱情 | F13: Tình yêu & Hôn nhân | G13: 9 | H13: 从来 | I13: cóng lái | J13: Phó từ | K13: từ trước đến nay | L13: https://xiehanzi.com/thu-vien-hsk/hsk-4/bai-hoc/bai-1-tinh-yeu-don-gian/
A14: 10 | B14: HSK 4 | C14: Bài 01 | D14: Tình yêu đơn giản | E14: 简单的爱情 | F14: Tình yêu & Hôn nhân | G14: 10 | H14: 最好 | I14: zuì hǎo | J14: Phó từ | K14: tốt nhất là | L14: https://xiehanzi.com/thu-vien-hsk/hsk-4/bai-hoc/bai-1-tinh-yeu-don-gian/
A15: 11 | B15: HSK 4 | C15: Bài 01 | D15: Tình yêu đơn giản | E15: 简单的爱情 | F15: Tình yêu & Hôn nhân | G15: 11 | H15: 共同 | I15: gòng tóng | J15: Tính từ | K15: chung, cùng | L15: https://xiehanzi.com/thu-vien-hsk/hsk-4/bai-hoc/bai-1-tinh-yeu-don-gian/
A16: 12 | B16: HSK 4 | C16: Bài 01 | D16: Tình yêu đơn giản | E16: 简单的爱情 | F16: Tình yêu & Hôn nhân | G16: 12 | H16: 适合 | I16: shì hé | J16: Động từ | K16: phù hợp, thích hợp | L16: https://xiehanzi.com/thu-vien-hsk/hsk-4/bai-hoc/bai-1-tinh-yeu-don-gian/
... A626: 622 | B626: HSK 4 | C626: Bài 20 | D626: Phong cảnh trên đường | E626: 路上的风景 | F626: Du lịch & Văn hóa vùng miền | G626: 30 | H626: 酸 | I626: suān | J626: Tính từ | K626: chua, mỏi | L626: https://xiehanzi.com/thu-vien-hsk/hsk-4/bai-hoc/bai-20-phong-canh-tren-duong/
B627: Tổng cộng | C627: 20 bài học | D627: Toàn bộ từ vựng HSK 4 (20 bài) | F627: 26 chủ đề | G627: =COUNTA(H5:H626) | K627: Tổng số mục từ vựng trong 20 bài học HSK 4: 622 từ

Sheet HSK 5
A1: DANH SÁCH BÀI HỌC & TỪ VỰNG HSK 5 (CAO CẤP) — THƯ VIỆN XIEHANZI
A2: Trình độ: Cao cấp | Số bài học: 36 bài | Số chủ đề: 43 chủ đề | Từ chuẩn cấp HSK 5: 1,282 từ | Tổng lượt từ trong bài: 1,601 từ | Ngữ pháp: 101 điểm | Thời lượng: ~214 giờ | Nguồn: https://xiehanzi.com/thu-vien-hsk/hsk-5/
A4: STT | B4: Cấp HSK | C4: Bài số | D4: Tên bài học (Tiếng Việt) | E4: Tên bài học (Tiếng Trung) | F4: Chủ đề / Đơn nguyên | G4: STT trong bài | H4: Từ vựng (Chữ Hán) | I4: Phiên âm (Pinyin) | J4: Từ loại | K4: Nghĩa tiếng Việt | L4: Link bài học XieHanzi
A5: 1 | B5: HSK 5 | C5: Bài 01 | D5: Chi tiết của tình yêu | E5: 爱的细节 | F5: Tìm hiểu cuộc sống (了解生活) | G5: 1 | H5: 细节 | I5: xì jié | J5: Danh từ | K5: chi tiết | L5: https://xiehanzi.com/thu-vien-hsk/hsk-5/bai-hoc/bai-1-chi-tiet-cua-tinh-yeu/
A6: 2 | B6: HSK 5 | C6: Bài 01 | D6: Chi tiết của tình yêu | E6: 爱的细节 | F6: Tìm hiểu cuộc sống (了解生活) | G6: 2 | H6: 电台 | I6: diàn tái | J6: Danh từ | K6: đài phát thanh | L6: https://xiehanzi.com/thu-vien-hsk/hsk-5/bai-hoc/bai-1-chi-tiet-cua-tinh-yeu/
A7: 3 | B7: HSK 5 | C7: Bài 01 | D7: Chi tiết của tình yêu | E7: 爱的细节 | F7: Tìm hiểu cuộc sống (了解生活) | G7: 3 | H7: 恩爱 | I7: ēn ài | J7: Tính từ | K7: ân ái, yêu thương mặn nồng (vợ chồng) | L7: https://xiehanzi.com/thu-vien-hsk/hsk-5/bai-hoc/bai-1-chi-tiet-cua-tinh-yeu/
A8: 4 | B8: HSK 5 | C8: Bài 01 | D8: Chi tiết của tình yêu | E8: 爱的细节 | F8: Tìm hiểu cuộc sống (了解生活) | G8: 4 | H8: 对比 | I8: duì bǐ | J8: Động từ / Danh từ | K8: đối chiếu, so sánh | L8: https://xiehanzi.com/thu-vien-hsk/hsk-5/bai-hoc/bai-1-chi-tiet-cua-tinh-yeu/
A9: 5 | B9: HSK 5 | C9: Bài 01 | D9: Chi tiết của tình yêu | E9: 爱的细节 | F9: Tìm hiểu cuộc sống (了解生活) | G9: 5 | H9: 入围 | I9: rù wéi | J9: Động từ | K9: lọt vào vòng chung kết/đề cử | L9: https://xiehanzi.com/thu-vien-hsk/hsk-5/bai-hoc/bai-1-chi-tiet-cua-tinh-yeu/
A10: 6 | B10: HSK 5 | C10: Bài 01 | D10: Chi tiết của tình yêu | E10: 爱的细节 | F10: Tìm hiểu cuộc sống (了解生活) | G10: 6 | H10: 评委 | I10: píng wěi | J10: Danh từ | K10: ban giám khảo | L10: https://xiehanzi.com/thu-vien-hsk/hsk-5/bai-hoc/bai-1-chi-tiet-cua-tinh-yeu/
A11: 7 | B11: HSK 5 | C11: Bài 01 | D11: Chi tiết của tình yêu | E11: 爱的细节 | F11: Tìm hiểu cuộc sống (了解生活) | G11: 7 | H11: 如何 | I11: rú hé | J11: Đại từ | K11: như thế nào, ra sao | L11: https://xiehanzi.com/thu-vien-hsk/hsk-5/bai-hoc/bai-1-chi-tiet-cua-tinh-yeu/
A12: 8 | B12: HSK 5 | C12: Bài 01 | D12: Chi tiết của tình yêu | E12: 爱的细节 | F12: Tìm hiểu cuộc sống (了解生活) | G12: 8 | H12: 瘫痪 | I12: tān huàn | J12: Động từ | K12: bị liệt, tê liệt | L12: https://xiehanzi.com/thu-vien-hsk/hsk-5/bai-hoc/bai-1-chi-tiet-cua-tinh-yeu/
A13: 9 | B13: HSK 5 | C13: Bài 01 | D13: Chi tiết của tình yêu | E13: 爱的细节 | F13: Tìm hiểu cuộc sống (了解生活) | G13: 9 | H13: 离婚 | I13: lí hūn | J13: Động từ | K13: ly hôn | L13: https://xiehanzi.com/thu-vien-hsk/hsk-5/bai-hoc/bai-1-chi-tiet-cua-tinh-yeu/
A14: 10 | B14: HSK 5 | C14: Bài 01 | D14: Chi tiết của tình yêu | E14: 爱的细节 | F14: Tìm hiểu cuộc sống (了解生活) | G14: 10 | H14: 自杀 | I14: zì shā | J14: Động từ | K14: tự sát, tự tử | L14: https://xiehanzi.com/thu-vien-hsk/hsk-5/bai-hoc/bai-1-chi-tiet-cua-tinh-yeu/
A15: 11 | B15: HSK 5 | C15: Bài 01 | D15: Chi tiết của tình yêu | E15: 爱的细节 | F15: Tìm hiểu cuộc sống (了解生活) | G15: 11 | H15: 抱怨 | I15: bào yuàn | J15: Động từ | K15: phàn nàn, oán trách | L15: https://xiehanzi.com/thu-vien-hsk/hsk-5/bai-hoc/bai-1-chi-tiet-cua-tinh-yeu/
A16: 12 | B16: HSK 5 | C16: Bài 01 | D16: Chi tiết của tình yêu | E16: 爱的细节 | F16: Tìm hiểu cuộc sống (了解生活) | G16: 12 | H16: 爱护 | I16: ài hù | J16: Động từ | K16: yêu thương và bảo vệ, giữ gìn | L16: https://xiehanzi.com/thu-vien-hsk/hsk-5/bai-hoc/bai-1-chi-tiet-cua-tinh-yeu/
... A1252: 1248 | B1252: HSK 5 | C1252: Bài 36 | D1252: Lão Xá và việc trồng hoa | E1252: 老舍与养花 | F1252: Thiên nhiên và môi trường (自然与环境) | G1252: 37 | H1252: 热爱 | I1252: rè ài | J1252: Động từ | K1252: yêu tha thiết, đam mê | L1252: https://xiehanzi.com/thu-vien-hsk/hsk-5/bai-hoc/bai-36-lao-xa-va-viec-trong-hoa/
B1253: Tổng cộng | C1253: 36 bài học | D1253: Toàn bộ từ vựng HSK 5 (36 bài) | F1253: 43 chủ đề | G1253: =COUNTA(H5:H1252) | K1253: Tổng số mục từ vựng trong 36 bài học HSK 5: 1248 từ

Sheet HSK 6
A1: DANH SÁCH BÀI HỌC & TỪ VỰNG HSK 6 (CAO CẤP) — THƯ VIỆN XIEHANZI
A2: Trình độ: Cao cấp | Số bài học: 40 bài | Số chủ đề: 74 chủ đề | Từ chuẩn cấp HSK 6: 2,593 từ | Tổng lượt từ trong bài: 2,516 từ | Ngữ pháp: 63 điểm | Thời lượng: ~432 giờ | Nguồn: https://xiehanzi.com/thu-vien-hsk/hsk-6/
A4: STT | B4: Cấp HSK | C4: Bài số | D4: Tên bài học (Tiếng Việt) | E4: Tên bài học (Tiếng Trung) | F4: Chủ đề / Đơn nguyên | G4: STT trong bài | H4: Từ vựng (Chữ Hán) | I4: Phiên âm (Pinyin) | J4: Từ loại | K4: Nghĩa tiếng Việt | L4: Link bài học XieHanzi
A5: 1 | B5: HSK 6 | C5: Bài 01 | D5: Gợi mở từ con trẻ | E5: 孩子给我们的启示 | F5: Chuyện nhỏ cuộc sống (生活点滴) | G5: 1 | H5: 启示 | I5: qǐ shì | J5: Danh từ / Động từ | K5: gợi mở, bài học sâu sắc | L5: https://xiehanzi.com/thu-vien-hsk/hsk-6/bai-hoc/bai-1-goi-mo-tu-con-tre/
A6: 2 | B6: HSK 6 | C6: Bài 01 | D6: Gợi mở từ con trẻ | E6: 孩子给我们的启示 | F6: Chuyện nhỏ cuộc sống (生活点滴) | G6: 2 | H6: 老公 | I6: lǎo gōng | J6: Danh từ | K6: chồng, ông xã | L6: https://xiehanzi.com/thu-vien-hsk/hsk-6/bai-hoc/bai-1-goi-mo-tu-con-tre/
A7: 3 | B7: HSK 6 | C7: Bài 01 | D7: Gợi mở từ con trẻ | E7: 孩子给我们的启示 | F7: Chuyện nhỏ cuộc sống (生活点滴) | G7: 3 | H7: 爽快 | I7: shuǎng kuai | J7: Tính từ | K7: sảng khoái, thẳng thắn, mau lẹ | L7: https://xiehanzi.com/thu-vien-hsk/hsk-6/bai-hoc/bai-1-goi-mo-tu-con-tre/
A8: 4 | B8: HSK 6 | C8: Bài 01 | D8: Gợi mở từ con trẻ | E8: 孩子给我们的启示 | F8: Chuyện nhỏ cuộc sống (生活点滴) | G8: 4 | H8: 巴不得 | I8: bā bu dé | J8: Động từ | K8: chỉ mong sao, ước gì | L8: https://xiehanzi.com/thu-vien-hsk/hsk-6/bai-hoc/bai-1-goi-mo-tu-con-tre/
A9: 5 | B9: HSK 6 | C9: Bài 01 | D9: Gợi mở từ con trẻ | E9: 孩子给我们的启示 | F9: Chuyện nhỏ cuộc sống (生活点滴) | G9: 5 | H9: 嚷 | I9: rǎng | J9: Động từ | K9: la hét, kêu gào, đòi | L9: https://xiehanzi.com/thu-vien-hsk/hsk-6/bai-hoc/bai-1-goi-mo-tu-con-tre/
A10: 6 | B10: HSK 6 | C10: Bài 01 | D10: Gợi mở từ con trẻ | E10: 孩子给我们的启示 | F10: Chuyện nhỏ cuộc sống (生活点滴) | G10: 6 | H10: 拿手 | I10: ná shǒu | J10: Tính từ | K10: sở trường, giỏi nhất | L10: https://xiehanzi.com/thu-vien-hsk/hsk-6/bai-hoc/bai-1-goi-mo-tu-con-tre/
A11: 7 | B11: HSK 6 | C11: Bài 01 | D11: Gợi mở từ con trẻ | E11: 孩子给我们的启示 | F11: Chuyện nhỏ cuộc sống (生活点滴) | G11: 7 | H11: 佳肴 | I11: jiā yáo | J11: Danh từ | K11: món ngon, mỹ vị | L11: https://xiehanzi.com/thu-vien-hsk/hsk-6/bai-hoc/bai-1-goi-mo-tu-con-tre/
A12: 8 | B12: HSK 6 | C12: Bài 01 | D12: Gợi mở từ con trẻ | E12: 孩子给我们的启示 | F12: Chuyện nhỏ cuộc sống (生活点滴) | G12: 8 | H12: 异常 | I12: yì cháng | J12: Phó từ / Tính từ | K12: khác thường, vô cùng | L12: https://xiehanzi.com/thu-vien-hsk/hsk-6/bai-hoc/bai-1-goi-mo-tu-con-tre/
A13: 9 | B13: HSK 6 | C13: Bài 01 | D13: Gợi mở từ con trẻ | E13: 孩子给我们的启示 | F13: Chuyện nhỏ cuộc sống (生活点滴) | G13: 9 | H13: 勤劳 | I13: qín láo | J13: Tính từ | K13: cần cù, chịu khó | L13: https://xiehanzi.com/thu-vien-hsk/hsk-6/bai-hoc/bai-1-goi-mo-tu-con-tre/
A14: 10 | B14: HSK 6 | C14: Bài 01 | D14: Gợi mở từ con trẻ | E14: 孩子给我们的启示 | F14: Chuyện nhỏ cuộc sống (生活点滴) | G14: 10 | H14: 绅士 | I14: shēn shì | J14: Danh từ | K14: quý ông, lịch lãm | L14: https://xiehanzi.com/thu-vien-hsk/hsk-6/bai-hoc/bai-1-goi-mo-tu-con-tre/
A15: 11 | B15: HSK 6 | C15: Bài 01 | D15: Gợi mở từ con trẻ | E15: 孩子给我们的启示 | F15: Chuyện nhỏ cuộc sống (生活点滴) | G15: 11 | H15: 风度 | I15: fēng dù | J15: Danh từ | K15: phong độ, cốt cách | L15: https://xiehanzi.com/thu-vien-hsk/hsk-6/bai-hoc/bai-1-goi-mo-tu-con-tre/
A16: 12 | B16: HSK 6 | C16: Bài 01 | D16: Gợi mở từ con trẻ | E16: 孩子给我们的启示 | F16: Chuyện nhỏ cuộc sống (生活点滴) | G16: 12 | H16: 十足 | I16: shí zú | J16: Tính từ | K16: tràn đầy, mười phân vẹn mười | L16: https://xiehanzi.com/thu-vien-hsk/hsk-6/bai-hoc/bai-1-goi-mo-tu-con-tre/
... A1577: 1573 | B1577: HSK 6 | C1577: Bài 40 | D1577: Siêu năng lực của con người có làm thay đổi kỷ lục thế giới không? | E1577: 人类超能力会改变世界纪录吗 | F1577: Xã hội và thời đại (社会与时代) | G1577: 29 | H1577: 辉煌 | I1577: huī huáng | J1577: Tính từ / Danh từ | K1577: huy hoàng | L1577: https://xiehanzi.com/thu-vien-hsk/hsk-6/bai-hoc/bai-40-sieu-nang-luc-cua-con-nguoi-co-lam-thay-doi-ky-luc-the-gioi-khong/
B1578: Tổng cộng | C1578: 40 bài học | D1578: Toàn bộ từ vựng HSK 6 (40 bài) | F1578: 74 chủ đề | G1578: =COUNTA(H5:H1577) | K1578: Tổng số mục từ vựng trong 40 bài học HSK 6: 1573 từ

Sheet Từ vựng theo Chủ đề
A1: PHÂN LOẠI TỪ VỰNG THEO CHỦ ĐỀ & ĐƠN NGUYÊN (HSK 1 – HSK 6) | XIEHANZI
A2: Tổng hợp các nhóm chủ đề từ vựng từ HSK 1 đến HSK 6, các bài học tương ứng và danh sách từ vựng tiêu biểu trong từng chủ đề
A4: STT | B4: Cấp HSK | C4: Tên Chủ đề / Đơn nguyên (Topic) | D4: Các bài học thuộc chủ đề | E4: Số bài học | F4: Tổng số từ vựng | G4: Danh sách từ vựng trong chủ đề (Chữ Hán & Pinyin) | H4: Nghĩa tiếng Việt tiêu biểu | I4: Link thư viện XieHanzi
A5: 1 | B5: HSK 1 | C5: Chào hỏi & Giao tiếp cơ bản | D5: Bài 01: Xin chào (你好) | E5: 1 | F5: 6 | G5: 你 (nǐ), 好 (hǎo), 您 (nín), 你们 (nǐ men), 对不起 (duì bu qǐ), 没关系 (méi guān xi) | H5: 你: bạn, anh, chị (ngôi thứ 2 số ít); 好: tốt, khỏe, hay; 您: ông, bà, ngài (ngôi thứ 2 kính trọng); 你们: các bạn, các anh, các chị; 对不起: xin lỗi; 没关系: không sao, không có gì | I5: https://xiehanzi.com/thu-vien-hsk/hsk-1/
A6: 2 | B6: HSK 1 | C6: Lịch sự & Cảm ơn | D6: Bài 02: Cảm ơn bạn (谢谢你) | E6: 1 | F6: 4 | G6: 谢谢 (xiè xie), 不 (bù), 不客气 (bù kè qi), 再见 (zài jiàn) | H6: 谢谢: cảm ơn; 不: không; 不客气: đừng khách sáo, không có chi; 再见: tạm biệt, hẹn gặp lại | I6: https://xiehanzi.com/thu-vien-hsk/hsk-1/
A7: 3 | B7: HSK 1 | C7: Giới thiệu bản thân & Quốc tịch | D7: Bài 03: Bạn tên là gì? (你叫什么名字) | E7: 1 | F7: 9 | G7: 叫 (jiào), 什么 (shén me), 名字 (míng zi), 我 (wǒ), 是 (shì), 老师 (lǎo shī), 吗 (ma), 学生 (xué sheng), 人 (rén) | H7: 叫: gọi, tên là; 什么: cái gì, gì; 名字: tên; 我: tôi, mình; 是: là; 老师: giáo viên, thầy/cô giáo; 吗: không, à (trợ từ nghi vấn cuối câu); 学生: học sinh, sinh viên; 人: người | I7: https://xiehanzi.com/thu-vien-hsk/hsk-1/
A8: 4 | B8: HSK 1 | C8: Trường học & Bạn bè | D8: Bài 04: Cô ấy là giáo viên tiếng Hán của tôi (她是我的汉语老师) | E8: 1 | F8: 10 | G8: 她 (tā), 谁 (shéi / shuí), 的 (de), 汉语 (Hàn yǔ), 哪 (nǎ), 国 (guó), 呢 (ne), 他 (tā), 同学 (tóng xué), 朋友 (péng you) | H8: 她: cô ấy, bà ấy, chị ấy; 谁: ai; 的: của (trợ từ kết cấu biểu thị sở hữu); 汉语: tiếng Hán, tiếng Trung; 哪: nào; 国: nước, quốc gia; 呢: thế, nhỉ, thì sao (trợ từ ngữ khí); 他: anh ấy, ông ấy; 同学: bạn cùng học, bạn học; 朋友: bạn, bạn bè | I8: https://xiehanzi.com/thu-vien-hsk/hsk-1/
A9: 5 | B9: HSK 1 | C9: Gia đình & Tuổi tác | D9: Bài 05: Con gái cô ấy năm nay 20 tuổi (她女儿今年二十岁) | E9: 1 | F9: 10 | G9: 家 (jiā), 有 (yǒu), 口 (kǒu), 女儿 (nǚ'ér), 几 (jǐ), 岁 (suì), 了 (le), 今年 (jīn nián), 多 (duō), 大 (dà) | H9: 家: nhà, gia đình; 有: có; 口: miệng; lượng từ chỉ người trong gia đình; 女儿: con gái; 几: mấy, vài; 岁: tuổi; 了: rồi, đã (trợ từ ngữ khí/động thái); 今年: năm nay; 多: bao nhiêu; nhiều; 大: to, lớn (nhiều tuổi) | I9: https://xiehanzi.com/thu-vien-hsk/hsk-1/
A10: 6 | B10: HSK 1 | C10: Kỹ năng & Ngôn ngữ | D10: Bài 06: Tôi biết nói tiếng Hán (我会说汉语) | E10: 1 | F10: 12 | G10: 会 (huì), 说 (shuō), 妈妈 (mā ma), 菜 (cài), 很 (hěn), 好吃 (hǎo chī), 做 (zuò), 写 (xiě), 汉字 (Hàn zì), 字 (zì), 怎么 (zěn me), 读 (dú) | H10: 会: biết (thông qua học tập), sẽ; 说: nói; 妈妈: mẹ; 菜: món ăn, thức ăn, rau; 很: rất; 好吃: ngon, dễ ăn; 做: làm, nấu; 写: viết; 汉字: chữ Hán; 字: chữ, từ ... | I10: https://xiehanzi.com/thu-vien-hsk/hsk-1/
A11: 7 | B11: HSK 1 | C11: Thời gian & Ngày tháng | D11: Bài 07: Hôm nay là ngày mấy? (今天几号) | E11: 1 | F11: 12 | G11: 请 (qǐng), 问 (wèn), 今天 (jīn tiān), 号 (hào), 月 (yuè), 星期 (xīng qī), 昨天 (zuó tiān), 明天 (míng tiān), 去 (qù), 学校 (xué xiào), 看 (kàn), 书 (shū) | H11: 请: mời, xin; 问: hỏi; 今天: hôm nay; 号: ngày (trong tháng), số; 月: tháng, mặt trăng; 星期: tuần, thứ; 昨天: hôm qua; 明天: ngày mai; 去: đi; 学校: trường học ... | I11: https://xiehanzi.com/thu-vien-hsk/hsk-1/
A12: 8 | B12: HSK 1 | C12: Thức ăn, Đồ uống & Mua sắm | D12: Bài 08: Tôi muốn uống trà (我想喝茶) | E12: 1 | F12: 15 | G12: 想 (xiǎng), 喝 (hē), 茶 (chá), 吃 (chī), 米饭 (mǐ fàn), 下午 (xià wǔ), 商店 (shāng diàn), 买 (mǎi), 个 (gè), 杯子 (bēi zi), 这 (zhè), 多少 (duō shao), 钱 (qián), 块 (kuài), 那 (nà) | H12: 想: muốn, nghĩ, nhớ; 喝: uống; 茶: trà, chè; 吃: ăn; 米饭: cơm; 下午: buổi chiều; 商店: cửa hàng, tiệm tạp hóa; 买: mua; 个: cái, chiếc, người (lượng từ phổ biến); 杯子: cái cốc, cái ly ... | I12: https://xiehanzi.com/thu-vien-hsk/hsk-1/
A13: 9 | B13: HSK 1 | C13: Nơi chốn & Nghề nghiệp | D13: Bài 09: Con trai bạn làm việc ở đâu? (你儿子在哪儿工作) | E13: 1 | F13: 13 | G13: 小 (xiǎo), 猫 (māo), 在 (zài), 那儿 (nàr), 狗 (gǒu), 椅子 (yǐ zi), 下面 (xià miàn), 哪儿 (nǎr), 工作 (gōng zuò), 儿子 (ér zi), 医院 (yī yuàn), 医生 (yī shēng), 爸爸 (bà ba) | H13: 小: nhỏ, bé; 猫: con mèo; 在: ở, tại; đang; 那儿: chỗ đó, ở đó; 狗: con chó; 椅子: cái ghế; 下面: phía dưới, bên dưới; 哪儿: ở đâu, chỗ nào; 工作: làm việc; công việc; 儿子: con trai ... | I13: https://xiehanzi.com/thu-vien-hsk/hsk-1/
A14: 10 | B14: HSK 1 | C14: Vị trí & Đồ vật | D14: Bài 10: Tôi có thể ngồi đây không? (我能坐这儿吗) | E14: 1 | F14: 12 | G14: 桌子 (zhuō zi), 上 (shàng), 电脑 (diàn nǎo), 和 (hé), 本 (běn), 里 (lǐ), 前面 (qián miàn), 后面 (hòu miàn), 这儿 (zhèr), 没有 (méi yǒu), 能 (néng), 坐 (zuò) | H14: 桌子: cái bàn; 上: trên, phía trên; 电脑: máy vi tính; 和: và, với; 本: quyển, cuốn (dùng cho sách, vở); 里: bên trong, trong; 前面: phía trước, đằng trước; 后面: phía sau, đằng sau; 这儿: ở đây, chỗ này; 没有: không có, chưa ... | I14: https://xiehanzi.com/thu-vien-hsk/hsk-1/
A15: 11 | B15: HSK 1 | C15: Thời gian & Sinh hoạt | D15: Bài 11: Bây giờ mấy giờ rồi? (现在几点) | E15: 1 | F15: 11 | G15: 现在 (xiàn zài), 点 (diǎn), 分 (fēn), 中午 (zhōng wǔ), 吃饭 (chī fàn), 时候 (shí hou), 回 (huí), 我们 (wǒ men), 电影 (diàn yǐng), 住 (zhù), 前 (qián) | H15: 现在: bây giờ, hiện tại; 点: giờ (trên đồng hồ); 分: phút; 中午: buổi trưa; 吃饭: ăn cơm; 时候: thời gian, lúc, khi; 回: về, trở về; 我们: chúng tôi, chúng ta; 电影: phim, điện ảnh; 住: sống, ở, cư trú ... | I15: https://xiehanzi.com/thu-vien-hsk/hsk-1/
A16: 12 | B16: HSK 1 | C16: Thời tiết & Sức khỏe | D16: Bài 12: Ngày mai thời tiết thế nào? (明天天气怎么样) | E16: 1 | F16: 15 | G16: 天气 (tiān qì), 怎么样 (zěn me yàng), 太 (tài), 热 (rè), 冷 (lěng), 下雨 (xià yǔ), 小姐 (xiǎo jiě), 来 (lái), 雨 (yǔ), 下 (xià), 身体 (shēn tǐ), 爱 (ài), 些 (xiē), 水果 (shuǐ guǒ), 水 (shuǐ) | H16: 天气: thời tiết; 怎么样: như thế nào, ra sao; 太: quá, lắm; 热: nóng; 冷: lạnh; 下雨: mưa, đổ mưa; 小姐: cô, tiểu thư; 来: đến, tới; 雨: mưa; 下: rơi, xuống; dưới, sau ... | I16: https://xiehanzi.com/thu-vien-hsk/hsk-1/
... A96: 92 | B96: HSK 6 | C96: Xã hội và thời đại (社会与时代) | D96: Bài 37: Câu chuyện của cảnh sát (警察的故事) Bài 38: Đôi mắt tinh tường nắm bắt cơ hội kinh doanh (慧眼捕捉商机) Bài 39: Cuộc sống thời đại Internet (互联网时代的生活) Bài 40: Siêu năng lực của con người có làm thay đổi kỷ lục thế giới không? (人类超能力会改变世界纪录吗) | E96: 4 | F96: 230 | G96: 巡逻 (xún luó), 执勤 (zhí qín), 蛛丝马迹 (zhū sī mǎ jì), 敏锐 (mǐn ruì), 洞察 (dòng chá), 可疑 (kě yí), 盘问 (pán wèn), 神色 (shén sè), 慌乱 (huāng luàn), 破绽 (pò zhàn), 搏斗 (bó dòu), 制服 (zhì fú), 歹徒 (dǎi tú), 凶器 (xiōng qì), 挺身而出 (tǐng shēn ér chū), 负伤 (fù shāng), 审讯 (shěn xùn), 水落石出 (shuǐ luò shí chū) ... (+212 từ) | H96: 巡逻: tuần tra; 执勤: trực ban, làm nhiệm vụ; 蛛丝马迹: manh mối nhỏ nhất; 敏锐: nhạy bén; 洞察: nhận biết sâu sắc; 可疑: đáng ngờ, khả nghi; 盘问: tra hỏi, xét hỏi; 神色: thần sắc, vẻ mặt; 慌乱: hoảng loạn, luống cuống; 破绽: sơ hở ... | I96: https://xiehanzi.com/thu-vien-hsk/hsk-6/
B97: Tổng cộng | C97: 92 nhóm chủ đề / đơn nguyên | E97: =SUM(E5:E96) | F97: =SUM(F5:F96)
